dtool_lookup_api/__init__.py
dtool_lookup_api/asynchronous.py
dtool_lookup_api/synchronous.py
dtool_lookup_api/version.py
dtool_lookup_api/core/LookupClient.py
dtool_lookup_api/core/__init__.py
dtool_lookup_api/core/config.py
dtool_lookup_api-0.10.3.dist-info/LICENSE.rst
dtool_lookup_api-0.10.3.dist-info/METADATA
dtool_lookup_api-0.10.3.dist-info/WHEEL
dtool_lookup_api-0.10.3.dist-info/top_level.txt
dtool_lookup_api-0.10.3.dist-info/RECORD
