Metadata-Version: 2.1
Name: dtool-lookup-api
Version: 0.10.3
Summary: This package offers both synchronous and asynchronous implementations of a standardized Python API to communicate with dserver.
Author-email: "Johannes L. Hörmann" <johannes.laurin@gmail.com>
Project-URL: Documentation, https://dtool-lookup-api.readthedocs.io
Project-URL: Repository, https://github.com/livMatS/dtool-lookup-api
Project-URL: Changelog, https://github.com/livMatS/dtool-lookup-api/blob/main/CHANGELOG.rst
License-File: LICENSE.rst
Requires-Dist: asgiref
Requires-Dist: aiohttp
Requires-Dist: dtoolcore >=3.9.0
Requires-Dist: certifi
Requires-Dist: PyYAML
Provides-Extra: docs
Requires-Dist: sphinx ; extra == 'docs'
Requires-Dist: sphinx-rtd-theme ; extra == 'docs'
Requires-Dist: sphinxcontrib-spelling ; extra == 'docs'
Provides-Extra: test
Requires-Dist: pytest ; extra == 'test'
Requires-Dist: pytest-cov ; extra == 'test'
